tomobar/__init__.py
tomobar/fourier.py
tomobar/methodsDIR.py
tomobar/methodsDIR_CuPy.py
tomobar/methodsIR.py
tomobar/methodsIR_CuPy.py
tomobar/regularisers.py
tomobar/regularisersCuPy.py
tomobar/astra_wrappers/__init__.py
tomobar/astra_wrappers/astra_base.py
tomobar/astra_wrappers/astra_tools2d.py
tomobar/astra_wrappers/astra_tools3d.py
tomobar/cuda_kernels/__init__.py
tomobar/cuda_kernels/fft_us_kernels.cu
tomobar/cuda_kernels/generate_filtersync.cu
tomobar/cuda_kernels/primal_dual_for_total_variation.cu
tomobar/cuda_kernels/rudin_osher_fatemi_total_variation.cu
tomobar/supp/__init__.py
tomobar/supp/dicts.py
tomobar/supp/funcs.py
tomobar/supp/suppTools.py
tomobar-2026.1.0.1.dist-info/licenses/LICENSE
tomobar-2026.1.0.1.dist-info/METADATA
tomobar-2026.1.0.1.dist-info/WHEEL
tomobar-2026.1.0.1.dist-info/top_level.txt
tomobar-2026.1.0.1.dist-info/RECORD
