Metadata-Version: 2.4
Name: tomobar
Version: 2026.1.0.1
Summary: TOmographic MOdel-BAsed Reconstruction (ToMoBAR) software
Author-email: Daniil Kazantsev <daniil.kazantsev@diamond.ac.uk>, Viktor Nikitin <vnikitin@anl.gov>
License: GPLv3
Project-URL: Repository, https://github.com/dkazanc/ToMoBAR
Classifier: Development Status :: 4 - Beta
Classifier: License :: OSI Approved :: GNU General Public License v3 (GPLv3)
Classifier: Programming Language :: Python :: 3.10
Classifier: Environment :: GPU :: NVIDIA CUDA
Requires-Python: >=3.10
License-File: LICENSE
Requires-Dist: numpy
Requires-Dist: cupy
Requires-Dist: astra-toolbox>=2.3.0
Requires-Dist: scipy
Requires-Dist: pillow
Requires-Dist: scikit-image
Provides-Extra: dev
Requires-Dist: pytest; extra == "dev"
Requires-Dist: pytest-cov; extra == "dev"
Requires-Dist: pytest-xdist; extra == "dev"
Requires-Dist: flake8; extra == "dev"
Requires-Dist: pyproject-flake8; extra == "dev"
Requires-Dist: pydocstyle; extra == "dev"
Requires-Dist: toml; extra == "dev"
Requires-Dist: imageio; extra == "dev"
Requires-Dist: h5py; extra == "dev"
Dynamic: license-file
